mediffusion/__init__.py
mediffusion/ddpm.py
mediffusion/trainer.py
mediffusion/default_config/__init__.py
mediffusion/default_config/default.yaml
mediffusion/diffusion/__init__.py
mediffusion/diffusion/base.py
mediffusion/diffusion/solvers.py
mediffusion/losses/__init__.py
mediffusion/losses/diffusion.py
mediffusion/models/__init__.py
mediffusion/models/unet.py
mediffusion/modules/__init__.py
mediffusion/modules/attention.py
mediffusion/modules/nn.py
mediffusion/modules/res.py
mediffusion/utils/__init__.py
mediffusion/utils/diffusion.py
mediffusion/utils/pl.py
mediffusion/utils/prediction.py
mediffusion/utils/solvers.py
mediffusion-0.7.1.dist-info/METADATA
mediffusion-0.7.1.dist-info/WHEEL
mediffusion-0.7.1.dist-info/top_level.txt
mediffusion-0.7.1.dist-info/RECORD
