Metadata-Version: 2.1
Name: mediffusion
Version: 0.7.1
Summary: Diffusion Models for Medical Imaging
Home-page: https://github.com/BardiaKh/Mediffusion
Author: Bardia Khosravi
Author-email: bardiakhosravi95@gmail.com
Classifier: Programming Language :: Python :: 3
Classifier: License :: OSI Approved :: MIT License
Classifier: Operating System :: OS Independent
Requires-Python: >=3.8
Requires-Dist: bkh-pytorch-utils ==0.9.3
Requires-Dist: torchextractor ==0.3.0
Requires-Dist: OmegaConf ==2.3.0
